LICENSE
MANIFEST.in
README.md
setup.cfg
setup.py
bin/zambeze
bin/zambeze-agent
examples/__init__.py
examples/imagemagick-globus.py
examples/imagemagick_files.py
zambeze/__init__.py
zambeze/actions.py
zambeze/config.py
zambeze/settings.py
zambeze/task.py
zambeze/version.py
zambeze.egg-info/PKG-INFO
zambeze.egg-info/SOURCES.txt
zambeze.egg-info/dependency_links.txt
zambeze.egg-info/requires.txt
zambeze.egg-info/top_level.txt
zambeze/campaign/__init__.py
zambeze/campaign/campaign.py
zambeze/campaign/activities/__init__.py
zambeze/campaign/activities/abstract_activity.py
zambeze/campaign/activities/shell.py
zambeze/db/zambeze_schema.sql
zambeze/orchestration/__init__.py
zambeze/orchestration/executor.py
zambeze/orchestration/identity.py
zambeze/orchestration/network.py
zambeze/orchestration/plugins.py
zambeze/orchestration/plugins_message_template_engine.py
zambeze/orchestration/plugins_message_validator.py
zambeze/orchestration/system_utils.py
zambeze/orchestration/zambeze_types.py
zambeze/orchestration/agent/__init__.py
zambeze/orchestration/agent/agent.py
zambeze/orchestration/agent/commands.py
zambeze/orchestration/agent/message_handler.py
zambeze/orchestration/agent/temp_activity_to_plugin_map.py
zambeze/orchestration/db/__init__.py
zambeze/orchestration/db/dao/__init__.py
zambeze/orchestration/db/dao/abstract_dao.py
zambeze/orchestration/db/dao/activity_dao.py
zambeze/orchestration/db/dao/dao_utils.py
zambeze/orchestration/db/model/__init__.py
zambeze/orchestration/db/model/abstract_entity.py
zambeze/orchestration/db/model/activity_model.py
zambeze/orchestration/message/__init__.py
zambeze/orchestration/message/abstract_message.py
zambeze/orchestration/message/abstract_message_validator.py
zambeze/orchestration/message/general_message_components.py
zambeze/orchestration/message/message_factory.py
zambeze/orchestration/message/transfer_hippo.py
zambeze/orchestration/message/activity_message/__init__.py
zambeze/orchestration/message/activity_message/message_activity.py
zambeze/orchestration/message/activity_message/message_activity_template_generator.py
